<?xml version="1.0" encoding="UTF-8" ?>
<lfm status="ok"><toptracks artist="Tiësto" page="1" perPage="50" totalPages="3952" total="197556"><track rank="1"><name>Adagio for Strings</name>
<playcount>1932455</playcount>
<listeners>344139</listeners>
<mbid>59be4709-45be-4296-88f5-fe59bde2eaef</mbid>
<url>https://www.last.fm/music/Ti%C3%ABsto/_/Adagio+for+Strings</url>
<streamable>0</streamable>
<artist><name>Tiësto</name>
<mbid>aabb1d9f-be12-45b3-a84d-a1fc3e8181fd</mbid>
<url>https://www.last.fm/music/Ti%C3%ABsto</url>
</artist>
<image size="small">https://lastfm.freetls.fastly.net/i/u/34s/2a96cbd8b46e442fc41c2b86b821562f.png</image>
<image size="medium">https://lastfm.freetls.fastly.net/i/u/64s/2a96cbd8b46e442fc41c2b86b821562f.png</image>
<image size="large">https://lastfm.freetls.fastly.net/i/u/174s/2a96cbd8b46e442fc41c2b86b821562f.png</image>
<image size="extralarge">https://lastfm.freetls.fastly.net/i/u/300x300/2a96cbd8b46e442fc41c2b86b821562f.png</image>
</track>
<track rank="2"><name>The Business</name>
<playcount>2705677</playcount>
<listeners>331180</listeners>
<url>https://www.last.fm/music/Ti%C3%ABsto/_/The+Business</url>
<streamable>0</streamable>
<artist><name>Tiësto</name>
<mbid>aabb1d9f-be12-45b3-a84d-a1fc3e8181fd</mbid>
<url>https://www.last.fm/music/Ti%C3%ABsto</url>
</artist>
<image size="small">https://lastfm.freetls.fastly.net/i/u/34s/2a96cbd8b46e442fc41c2b86b821562f.png</image>
<image size="medium">https://lastfm.freetls.fastly.net/i/u/64s/2a96cbd8b46e442fc41c2b86b821562f.png</image>
<image size="large">https://lastfm.freetls.fastly.net/i/u/174s/2a96cbd8b46e442fc41c2b86b821562f.png</image>
<image size="extralarge">https://lastfm.freetls.fastly.net/i/u/300x300/2a96cbd8b46e442fc41c2b86b821562f.png</image>
</track>
<track rank="3"><name>Wasted</name>
<playcount>1715906</playcount>
<listeners>310653</listeners>
<url>https://www.last.fm/music/Ti%C3%ABsto/_/Wasted</url>
<streamable>0</streamable>
<artist><name>Tiësto</name>
<mbid>aabb1d9f-be12-45b3-a84d-a1fc3e8181fd</mbid>
<url>https://www.last.fm/music/Ti%C3%ABsto</url>
</artist>
<image size="small">https://lastfm.freetls.fastly.net/i/u/34s/2a96cbd8b46e442fc41c2b86b821562f.png</image>
<image size="medium">https://lastfm.freetls.fastly.net/i/u/64s/2a96cbd8b46e442fc41c2b86b821562f.png</image>
<image size="large">https://lastfm.freetls.fastly.net/i/u/174s/2a96cbd8b46e442fc41c2b86b821562f.png</image>
<image size="extralarge">https://lastfm.freetls.fastly.net/i/u/300x300/2a96cbd8b46e442fc41c2b86b821562f.png</image>
</track>
<track rank="4"><name>The Motto</name>
<playcount>2974134</playcount>
<listeners>298894</listeners>
<url>https://www.last.fm/music/Ti%C3%ABsto/_/The+Motto</url>
<streamable>0</streamable>
<artist><name>Tiësto</name>
<mbid>aabb1d9f-be12-45b3-a84d-a1fc3e8181fd</mbid>
<url>https://www.last.fm/music/Ti%C3%ABsto</url>
</artist>
<image size="small">https://lastfm.freetls.fastly.net/i/u/34s/2a96cbd8b46e442fc41c2b86b821562f.png</image>
<image size="medium">https://lastfm.freetls.fastly.net/i/u/64s/2a96cbd8b46e442fc41c2b86b821562f.png</image>
<image size="large">https://lastfm.freetls.fastly.net/i/u/174s/2a96cbd8b46e442fc41c2b86b821562f.png</image>
<image size="extralarge">https://lastfm.freetls.fastly.net/i/u/300x300/2a96cbd8b46e442fc41c2b86b821562f.png</image>
</track>
<track rank="5"><name>Jackie Chan</name>
<playcount>2067840</playcount>
<listeners>291961</listeners>
<url>https://www.last.fm/music/Ti%C3%ABsto/_/Jackie+Chan</url>
<streamable>0</streamable>
<artist><name>Tiësto</name>
<mbid>aabb1d9f-be12-45b3-a84d-a1fc3e8181fd</mbid>
<url>https://www.last.fm/music/Ti%C3%ABsto</url>
</artist>
<image size="small">https://lastfm.freetls.fastly.net/i/u/34s/2a96cbd8b46e442fc41c2b86b821562f.png</image>
<image size="medium">https://lastfm.freetls.fastly.net/i/u/64s/2a96cbd8b46e442fc41c2b86b821562f.png</image>
<image size="large">https://lastfm.freetls.fastly.net/i/u/174s/2a96cbd8b46e442fc41c2b86b821562f.png</image>
<image size="extralarge">https://lastfm.freetls.fastly.net/i/u/300x300/2a96cbd8b46e442fc41c2b86b821562f.png</image>
</track>
<track rank="6"><name>Red Lights</name>
<playcount>1562795</playcount>
<listeners>258492</listeners>
<mbid>7098dc79-625e-4571-bf33-da740bc5b140</mbid>
<url>https://www.last.fm/music/Ti%C3%ABsto/_/Red+Lights</url>
<streamable>0</streamable>
<artist><name>Tiësto</name>
<mbid>aabb1d9f-be12-45b3-a84d-a1fc3e8181fd</mbid>
<url>https://www.last.fm/music/Ti%C3%ABsto</url>
</artist>
<image size="small">https://lastfm.freetls.fastly.net/i/u/34s/2a96cbd8b46e442fc41c2b86b821562f.png</image>
<image size="medium">https://lastfm.freetls.fastly.net/i/u/64s/2a96cbd8b46e442fc41c2b86b821562f.png</image>
<image size="large">https://lastfm.freetls.fastly.net/i/u/174s/2a96cbd8b46e442fc41c2b86b821562f.png</image>
<image size="extralarge">https://lastfm.freetls.fastly.net/i/u/300x300/2a96cbd8b46e442fc41c2b86b821562f.png</image>
</track>
<track rank="7"><name>10:35</name>
<playcount>1959521</playcount>
<listeners>257929</listeners>
<url>https://www.last.fm/music/Ti%C3%ABsto/_/10:35</url>
<streamable>0</streamable>
<artist><name>Tiësto</name>
<mbid>aabb1d9f-be12-45b3-a84d-a1fc3e8181fd</mbid>
<url>https://www.last.fm/music/Ti%C3%ABsto</url>
</artist>
<image size="small">https://lastfm.freetls.fastly.net/i/u/34s/2a96cbd8b46e442fc41c2b86b821562f.png</image>
<image size="medium">https://lastfm.freetls.fastly.net/i/u/64s/2a96cbd8b46e442fc41c2b86b821562f.png</image>
<image size="large">https://lastfm.freetls.fastly.net/i/u/174s/2a96cbd8b46e442fc41c2b86b821562f.png</image>
<image size="extralarge">https://lastfm.freetls.fastly.net/i/u/300x300/2a96cbd8b46e442fc41c2b86b821562f.png</image>
</track>
<track rank="8"><name>HoT iN iT</name>
<playcount>2424269</playcount>
<listeners>244714</listeners>
<url>https://www.last.fm/music/Ti%C3%ABsto/_/HoT+iN+iT</url>
<streamable>0</streamable>
<artist><name>Tiësto</name>
<mbid>aabb1d9f-be12-45b3-a84d-a1fc3e8181fd</mbid>
<url>https://www.last.fm/music/Ti%C3%ABsto</url>
</artist>
<image size="small">https://lastfm.freetls.fastly.net/i/u/34s/2a96cbd8b46e442fc41c2b86b821562f.png</image>
<image size="medium">https://lastfm.freetls.fastly.net/i/u/64s/2a96cbd8b46e442fc41c2b86b821562f.png</image>
<image size="large">https://lastfm.freetls.fastly.net/i/u/174s/2a96cbd8b46e442fc41c2b86b821562f.png</image>
<image size="extralarge">https://lastfm.freetls.fastly.net/i/u/300x300/2a96cbd8b46e442fc41c2b86b821562f.png</image>
</track>
<track rank="9"><name>Traffic</name>
<playcount>997953</playcount>
<listeners>217490</listeners>
<mbid>a899ded8-f3ff-400f-8ccf-37593bab2b20</mbid>
<url>https://www.last.fm/music/Ti%C3%ABsto/_/Traffic</url>
<streamable>0</streamable>
<artist><name>Tiësto</name>
<mbid>aabb1d9f-be12-45b3-a84d-a1fc3e8181fd</mbid>
<url>https://www.last.fm/music/Ti%C3%ABsto</url>
</artist>
<image size="small">https://lastfm.freetls.fastly.net/i/u/34s/2a96cbd8b46e442fc41c2b86b821562f.png</image>
<image size="medium">https://lastfm.freetls.fastly.net/i/u/64s/2a96cbd8b46e442fc41c2b86b821562f.png</image>
<image size="large">https://lastfm.freetls.fastly.net/i/u/174s/2a96cbd8b46e442fc41c2b86b821562f.png</image>
<image size="extralarge">https://lastfm.freetls.fastly.net/i/u/300x300/2a96cbd8b46e442fc41c2b86b821562f.png</image>
</track>
<track rank="10"><name>Don&apos;t Be Shy</name>
<playcount>1262607</playcount>
<listeners>202444</listeners>
<url>https://www.last.fm/music/Ti%C3%ABsto/_/Don%27t+Be+Shy</url>
<streamable>0</streamable>
<artist><name>Tiësto</name>
<mbid>aabb1d9f-be12-45b3-a84d-a1fc3e8181fd</mbid>
<url>https://www.last.fm/music/Ti%C3%ABsto</url>
</artist>
<image size="small">https://lastfm.freetls.fastly.net/i/u/34s/2a96cbd8b46e442fc41c2b86b821562f.png</image>
<image size="medium">https://lastfm.freetls.fastly.net/i/u/64s/2a96cbd8b46e442fc41c2b86b821562f.png</image>
<image size="large">https://lastfm.freetls.fastly.net/i/u/174s/2a96cbd8b46e442fc41c2b86b821562f.png</image>
<image size="extralarge">https://lastfm.freetls.fastly.net/i/u/300x300/2a96cbd8b46e442fc41c2b86b821562f.png</image>
</track>
<track rank="11"><name>Ritual</name>
<playcount>1404074</playcount>
<listeners>160521</listeners>
<url>https://www.last.fm/music/Ti%C3%ABsto/_/Ritual</url>
<streamable>0</streamable>
<artist><name>Tiësto</name>
<mbid>aabb1d9f-be12-45b3-a84d-a1fc3e8181fd</mbid>
<url>https://www.last.fm/music/Ti%C3%ABsto</url>
</artist>
<image size="small">https://lastfm.freetls.fastly.net/i/u/34s/2a96cbd8b46e442fc41c2b86b821562f.png</image>
<image size="medium">https://lastfm.freetls.fastly.net/i/u/64s/2a96cbd8b46e442fc41c2b86b821562f.png</image>
<image size="large">https://lastfm.freetls.fastly.net/i/u/174s/2a96cbd8b46e442fc41c2b86b821562f.png</image>
<image size="extralarge">https://lastfm.freetls.fastly.net/i/u/300x300/2a96cbd8b46e442fc41c2b86b821562f.png</image>
</track>
<track rank="12"><name>Lay Low</name>
<playcount>935008</playcount>
<listeners>152024</listeners>
<url>https://www.last.fm/music/Ti%C3%ABsto/_/Lay+Low</url>
<streamable>0</streamable>
<artist><name>Tiësto</name>
<mbid>aabb1d9f-be12-45b3-a84d-a1fc3e8181fd</mbid>
<url>https://www.last.fm/music/Ti%C3%ABsto</url>
</artist>
<image size="small">https://lastfm.freetls.fastly.net/i/u/34s/2a96cbd8b46e442fc41c2b86b821562f.png</image>
<image size="medium">https://lastfm.freetls.fastly.net/i/u/64s/2a96cbd8b46e442fc41c2b86b821562f.png</image>
<image size="large">https://lastfm.freetls.fastly.net/i/u/174s/2a96cbd8b46e442fc41c2b86b821562f.png</image>
<image size="extralarge">https://lastfm.freetls.fastly.net/i/u/300x300/2a96cbd8b46e442fc41c2b86b821562f.png</image>
</track>
<track rank="13"><name>Just Be</name>
<playcount>582260</playcount>
<listeners>126589</listeners>
<mbid>59a53e5c-940d-4da3-a92d-0042d17281ba</mbid>
<url>https://www.last.fm/music/Ti%C3%ABsto/_/Just+Be</url>
<streamable>0</streamable>
<artist><name>Tiësto</name>
<mbid>aabb1d9f-be12-45b3-a84d-a1fc3e8181fd</mbid>
<url>https://www.last.fm/music/Ti%C3%ABsto</url>
</artist>
<image size="small">https://lastfm.freetls.fastly.net/i/u/34s/2a96cbd8b46e442fc41c2b86b821562f.png</image>
<image size="medium">https://lastfm.freetls.fastly.net/i/u/64s/2a96cbd8b46e442fc41c2b86b821562f.png</image>
<image size="large">https://lastfm.freetls.fastly.net/i/u/174s/2a96cbd8b46e442fc41c2b86b821562f.png</image>
<image size="extralarge">https://lastfm.freetls.fastly.net/i/u/300x300/2a96cbd8b46e442fc41c2b86b821562f.png</image>
</track>
<track rank="14"><name>Love Comes Again</name>
<playcount>514020</playcount>
<listeners>119018</listeners>
<mbid>d2260e17-1f6f-409a-8311-2b205e63eb19</mbid>
<url>https://www.last.fm/music/Ti%C3%ABsto/_/Love+Comes+Again</url>
<streamable>0</streamable>
<artist><name>Tiësto</name>
<mbid>aabb1d9f-be12-45b3-a84d-a1fc3e8181fd</mbid>
<url>https://www.last.fm/music/Ti%C3%ABsto</url>
</artist>
<image size="small">https://lastfm.freetls.fastly.net/i/u/34s/2a96cbd8b46e442fc41c2b86b821562f.png</image>
<image size="medium">https://lastfm.freetls.fastly.net/i/u/64s/2a96cbd8b46e442fc41c2b86b821562f.png</image>
<image size="large">https://lastfm.freetls.fastly.net/i/u/174s/2a96cbd8b46e442fc41c2b86b821562f.png</image>
<image size="extralarge">https://lastfm.freetls.fastly.net/i/u/300x300/2a96cbd8b46e442fc41c2b86b821562f.png</image>
</track>
<track rank="15"><name>Elements Of Life</name>
<playcount>610520</playcount>
<listeners>116355</listeners>
<mbid>610d5e42-1593-4880-b3be-2bfd0ba33a02</mbid>
<url>https://www.last.fm/music/Ti%C3%ABsto/_/Elements+Of+Life</url>
<streamable>0</streamable>
<artist><name>Tiësto</name>
<mbid>aabb1d9f-be12-45b3-a84d-a1fc3e8181fd</mbid>
<url>https://www.last.fm/music/Ti%C3%ABsto</url>
</artist>
<image size="small">https://lastfm.freetls.fastly.net/i/u/34s/2a96cbd8b46e442fc41c2b86b821562f.png</image>
<image size="medium">https://lastfm.freetls.fastly.net/i/u/64s/2a96cbd8b46e442fc41c2b86b821562f.png</image>
<image size="large">https://lastfm.freetls.fastly.net/i/u/174s/2a96cbd8b46e442fc41c2b86b821562f.png</image>
<image size="extralarge">https://lastfm.freetls.fastly.net/i/u/300x300/2a96cbd8b46e442fc41c2b86b821562f.png</image>
</track>
<track rank="16"><name>BOOM</name>
<playcount>671173</playcount>
<listeners>116178</listeners>
<url>https://www.last.fm/music/Ti%C3%ABsto/_/BOOM</url>
<streamable>0</streamable>
<artist><name>Tiësto</name>
<mbid>aabb1d9f-be12-45b3-a84d-a1fc3e8181fd</mbid>
<url>https://www.last.fm/music/Ti%C3%ABsto</url>
</artist>
<image size="small">https://lastfm.freetls.fastly.net/i/u/34s/2a96cbd8b46e442fc41c2b86b821562f.png</image>
<image size="medium">https://lastfm.freetls.fastly.net/i/u/64s/2a96cbd8b46e442fc41c2b86b821562f.png</image>
<image size="large">https://lastfm.freetls.fastly.net/i/u/174s/2a96cbd8b46e442fc41c2b86b821562f.png</image>
<image size="extralarge">https://lastfm.freetls.fastly.net/i/u/300x300/2a96cbd8b46e442fc41c2b86b821562f.png</image>
</track>
<track rank="17"><name>Secrets - Radio Edit</name>
<playcount>693531</playcount>
<listeners>115635</listeners>
<url>https://www.last.fm/music/Ti%C3%ABsto/_/Secrets+-+Radio+Edit</url>
<streamable>0</streamable>
<artist><name>Tiësto</name>
<mbid>aabb1d9f-be12-45b3-a84d-a1fc3e8181fd</mbid>
<url>https://www.last.fm/music/Ti%C3%ABsto</url>
</artist>
<image size="small">https://lastfm.freetls.fastly.net/i/u/34s/2a96cbd8b46e442fc41c2b86b821562f.png</image>
<image size="medium">https://lastfm.freetls.fastly.net/i/u/64s/2a96cbd8b46e442fc41c2b86b821562f.png</image>
<image size="large">https://lastfm.freetls.fastly.net/i/u/174s/2a96cbd8b46e442fc41c2b86b821562f.png</image>
<image size="extralarge">https://lastfm.freetls.fastly.net/i/u/300x300/2a96cbd8b46e442fc41c2b86b821562f.png</image>
</track>
<track rank="18"><name>Lethal Industry</name>
<playcount>507225</playcount>
<listeners>112867</listeners>
<mbid>616ba9b3-0f22-4d33-b7dc-fa4457337f4e</mbid>
<url>https://www.last.fm/music/Ti%C3%ABsto/_/Lethal+Industry</url>
<streamable>0</streamable>
<artist><name>Tiësto</name>
<mbid>aabb1d9f-be12-45b3-a84d-a1fc3e8181fd</mbid>
<url>https://www.last.fm/music/Ti%C3%ABsto</url>
</artist>
<image size="small">https://lastfm.freetls.fastly.net/i/u/34s/2a96cbd8b46e442fc41c2b86b821562f.png</image>
<image size="medium">https://lastfm.freetls.fastly.net/i/u/64s/2a96cbd8b46e442fc41c2b86b821562f.png</image>
<image size="large">https://lastfm.freetls.fastly.net/i/u/174s/2a96cbd8b46e442fc41c2b86b821562f.png</image>
<image size="extralarge">https://lastfm.freetls.fastly.net/i/u/300x300/2a96cbd8b46e442fc41c2b86b821562f.png</image>
</track>
<track rank="19"><name>Forever Today</name>
<playcount>468248</playcount>
<listeners>108988</listeners>
<mbid>45b009e4-bb11-4458-bf48-5dd565bfb302</mbid>
<url>https://www.last.fm/music/Ti%C3%ABsto/_/Forever+Today</url>
<streamable>0</streamable>
<artist><name>Tiësto</name>
<mbid>aabb1d9f-be12-45b3-a84d-a1fc3e8181fd</mbid>
<url>https://www.last.fm/music/Ti%C3%ABsto</url>
</artist>
<image size="small">https://lastfm.freetls.fastly.net/i/u/34s/2a96cbd8b46e442fc41c2b86b821562f.png</image>
<image size="medium">https://lastfm.freetls.fastly.net/i/u/64s/2a96cbd8b46e442fc41c2b86b821562f.png</image>
<image size="large">https://lastfm.freetls.fastly.net/i/u/174s/2a96cbd8b46e442fc41c2b86b821562f.png</image>
<image size="extralarge">https://lastfm.freetls.fastly.net/i/u/300x300/2a96cbd8b46e442fc41c2b86b821562f.png</image>
</track>
<track rank="20"><name>Ten Seconds Before Sunrise</name>
<playcount>446568</playcount>
<listeners>101062</listeners>
<mbid>ce5904fc-16de-4ca8-800d-7a57178db9f8</mbid>
<url>https://www.last.fm/music/Ti%C3%ABsto/_/Ten+Seconds+Before+Sunrise</url>
<streamable>0</streamable>
<artist><name>Tiësto</name>
<mbid>aabb1d9f-be12-45b3-a84d-a1fc3e8181fd</mbid>
<url>https://www.last.fm/music/Ti%C3%ABsto</url>
</artist>
<image size="small">https://lastfm.freetls.fastly.net/i/u/34s/2a96cbd8b46e442fc41c2b86b821562f.png</image>
<image size="medium">https://lastfm.freetls.fastly.net/i/u/64s/2a96cbd8b46e442fc41c2b86b821562f.png</image>
<image size="large">https://lastfm.freetls.fastly.net/i/u/174s/2a96cbd8b46e442fc41c2b86b821562f.png</image>
<image size="extralarge">https://lastfm.freetls.fastly.net/i/u/300x300/2a96cbd8b46e442fc41c2b86b821562f.png</image>
</track>
<track rank="21"><name>Nyana</name>
<playcount>345061</playcount>
<listeners>95833</listeners>
<mbid>ec14f207-49ed-4350-bad8-c282df5b65a0</mbid>
<url>https://www.last.fm/music/Ti%C3%ABsto/_/Nyana</url>
<streamable>0</streamable>
<artist><name>Tiësto</name>
<mbid>aabb1d9f-be12-45b3-a84d-a1fc3e8181fd</mbid>
<url>https://www.last.fm/music/Ti%C3%ABsto</url>
</artist>
<image size="small">https://lastfm.freetls.fastly.net/i/u/34s/2a96cbd8b46e442fc41c2b86b821562f.png</image>
<image size="medium">https://lastfm.freetls.fastly.net/i/u/64s/2a96cbd8b46e442fc41c2b86b821562f.png</image>
<image size="large">https://lastfm.freetls.fastly.net/i/u/174s/2a96cbd8b46e442fc41c2b86b821562f.png</image>
<image size="extralarge">https://lastfm.freetls.fastly.net/i/u/300x300/2a96cbd8b46e442fc41c2b86b821562f.png</image>
</track>
<track rank="22"><name>God Is A Dancer (with Mabel)</name>
<playcount>617837</playcount>
<listeners>90201</listeners>
<url>https://www.last.fm/music/Ti%C3%ABsto/_/God+Is+A+Dancer+(with+Mabel)</url>
<streamable>0</streamable>
<artist><name>Tiësto</name>
<mbid>aabb1d9f-be12-45b3-a84d-a1fc3e8181fd</mbid>
<url>https://www.last.fm/music/Ti%C3%ABsto</url>
</artist>
<image size="small">https://lastfm.freetls.fastly.net/i/u/34s/2a96cbd8b46e442fc41c2b86b821562f.png</image>
<image size="medium">https://lastfm.freetls.fastly.net/i/u/64s/2a96cbd8b46e442fc41c2b86b821562f.png</image>
<image size="large">https://lastfm.freetls.fastly.net/i/u/174s/2a96cbd8b46e442fc41c2b86b821562f.png</image>
<image size="extralarge">https://lastfm.freetls.fastly.net/i/u/300x300/2a96cbd8b46e442fc41c2b86b821562f.png</image>
</track>
<track rank="23"><name>In The Dark</name>
<playcount>452224</playcount>
<listeners>89885</listeners>
<mbid>852eed64-641a-4f68-a2ca-9d35066bc76e</mbid>
<url>https://www.last.fm/music/Ti%C3%ABsto/_/In+The+Dark</url>
<streamable>0</streamable>
<artist><name>Tiësto</name>
<mbid>aabb1d9f-be12-45b3-a84d-a1fc3e8181fd</mbid>
<url>https://www.last.fm/music/Ti%C3%ABsto</url>
</artist>
<image size="small">https://lastfm.freetls.fastly.net/i/u/34s/2a96cbd8b46e442fc41c2b86b821562f.png</image>
<image size="medium">https://lastfm.freetls.fastly.net/i/u/64s/2a96cbd8b46e442fc41c2b86b821562f.png</image>
<image size="large">https://lastfm.freetls.fastly.net/i/u/174s/2a96cbd8b46e442fc41c2b86b821562f.png</image>
<image size="extralarge">https://lastfm.freetls.fastly.net/i/u/300x300/2a96cbd8b46e442fc41c2b86b821562f.png</image>
</track>
<track rank="24"><name>Carpe Noctum</name>
<playcount>324508</playcount>
<listeners>86061</listeners>
<mbid>ebdac766-f8e2-4dbf-95f8-223f5f419443</mbid>
<url>https://www.last.fm/music/Ti%C3%ABsto/_/Carpe+Noctum</url>
<streamable>0</streamable>
<artist><name>Tiësto</name>
<mbid>aabb1d9f-be12-45b3-a84d-a1fc3e8181fd</mbid>
<url>https://www.last.fm/music/Ti%C3%ABsto</url>
</artist>
<image size="small">https://lastfm.freetls.fastly.net/i/u/34s/2a96cbd8b46e442fc41c2b86b821562f.png</image>
<image size="medium">https://lastfm.freetls.fastly.net/i/u/64s/2a96cbd8b46e442fc41c2b86b821562f.png</image>
<image size="large">https://lastfm.freetls.fastly.net/i/u/174s/2a96cbd8b46e442fc41c2b86b821562f.png</image>
<image size="extralarge">https://lastfm.freetls.fastly.net/i/u/300x300/2a96cbd8b46e442fc41c2b86b821562f.png</image>
</track>
<track rank="25"><name>Secrets</name>
<playcount>534283</playcount>
<listeners>85774</listeners>
<url>https://www.last.fm/music/Ti%C3%ABsto/_/Secrets</url>
<streamable>0</streamable>
<artist><name>Tiësto</name>
<mbid>aabb1d9f-be12-45b3-a84d-a1fc3e8181fd</mbid>
<url>https://www.last.fm/music/Ti%C3%ABsto</url>
</artist>
<image size="small">https://lastfm.freetls.fastly.net/i/u/34s/2a96cbd8b46e442fc41c2b86b821562f.png</image>
<image size="medium">https://lastfm.freetls.fastly.net/i/u/64s/2a96cbd8b46e442fc41c2b86b821562f.png</image>
<image size="large">https://lastfm.freetls.fastly.net/i/u/174s/2a96cbd8b46e442fc41c2b86b821562f.png</image>
<image size="extralarge">https://lastfm.freetls.fastly.net/i/u/300x300/2a96cbd8b46e442fc41c2b86b821562f.png</image>
</track>
<track rank="26"><name>The Right Song</name>
<playcount>429981</playcount>
<listeners>82266</listeners>
<url>https://www.last.fm/music/Ti%C3%ABsto/_/The+Right+Song</url>
<streamable>0</streamable>
<artist><name>Tiësto</name>
<mbid>aabb1d9f-be12-45b3-a84d-a1fc3e8181fd</mbid>
<url>https://www.last.fm/music/Ti%C3%ABsto</url>
</artist>
<image size="small">https://lastfm.freetls.fastly.net/i/u/34s/2a96cbd8b46e442fc41c2b86b821562f.png</image>
<image size="medium">https://lastfm.freetls.fastly.net/i/u/64s/2a96cbd8b46e442fc41c2b86b821562f.png</image>
<image size="large">https://lastfm.freetls.fastly.net/i/u/174s/2a96cbd8b46e442fc41c2b86b821562f.png</image>
<image size="extralarge">https://lastfm.freetls.fastly.net/i/u/300x300/2a96cbd8b46e442fc41c2b86b821562f.png</image>
</track>
<track rank="27"><name>Maximal Crazy</name>
<playcount>319084</playcount>
<listeners>80265</listeners>
<mbid>295e5c8a-c25e-4e84-b414-e317ec94a7c6</mbid>
<url>https://www.last.fm/music/Ti%C3%ABsto/_/Maximal+Crazy</url>
<streamable>0</streamable>
<artist><name>Tiësto</name>
<mbid>aabb1d9f-be12-45b3-a84d-a1fc3e8181fd</mbid>
<url>https://www.last.fm/music/Ti%C3%ABsto</url>
</artist>
<image size="small">https://lastfm.freetls.fastly.net/i/u/34s/2a96cbd8b46e442fc41c2b86b821562f.png</image>
<image size="medium">https://lastfm.freetls.fastly.net/i/u/64s/2a96cbd8b46e442fc41c2b86b821562f.png</image>
<image size="large">https://lastfm.freetls.fastly.net/i/u/174s/2a96cbd8b46e442fc41c2b86b821562f.png</image>
<image size="extralarge">https://lastfm.freetls.fastly.net/i/u/300x300/2a96cbd8b46e442fc41c2b86b821562f.png</image>
</track>
<track rank="28"><name>Fresh Fruit</name>
<playcount>289500</playcount>
<listeners>78499</listeners>
<url>https://www.last.fm/music/Ti%C3%ABsto/_/Fresh+Fruit</url>
<streamable>0</streamable>
<artist><name>Tiësto</name>
<mbid>aabb1d9f-be12-45b3-a84d-a1fc3e8181fd</mbid>
<url>https://www.last.fm/music/Ti%C3%ABsto</url>
</artist>
<image size="small">https://lastfm.freetls.fastly.net/i/u/34s/2a96cbd8b46e442fc41c2b86b821562f.png</image>
<image size="medium">https://lastfm.freetls.fastly.net/i/u/64s/2a96cbd8b46e442fc41c2b86b821562f.png</image>
<image size="large">https://lastfm.freetls.fastly.net/i/u/174s/2a96cbd8b46e442fc41c2b86b821562f.png</image>
<image size="extralarge">https://lastfm.freetls.fastly.net/i/u/300x300/2a96cbd8b46e442fc41c2b86b821562f.png</image>
</track>
<track rank="29"><name>Walking On Clouds</name>
<playcount>321022</playcount>
<listeners>75966</listeners>
<url>https://www.last.fm/music/Ti%C3%ABsto/_/Walking+On+Clouds</url>
<streamable>0</streamable>
<artist><name>Tiësto</name>
<mbid>aabb1d9f-be12-45b3-a84d-a1fc3e8181fd</mbid>
<url>https://www.last.fm/music/Ti%C3%ABsto</url>
</artist>
<image size="small">https://lastfm.freetls.fastly.net/i/u/34s/2a96cbd8b46e442fc41c2b86b821562f.png</image>
<image size="medium">https://lastfm.freetls.fastly.net/i/u/64s/2a96cbd8b46e442fc41c2b86b821562f.png</image>
<image size="large">https://lastfm.freetls.fastly.net/i/u/174s/2a96cbd8b46e442fc41c2b86b821562f.png</image>
<image size="extralarge">https://lastfm.freetls.fastly.net/i/u/300x300/2a96cbd8b46e442fc41c2b86b821562f.png</image>
</track>
<track rank="30"><name>Driving To Heaven</name>
<playcount>281401</playcount>
<listeners>74669</listeners>
<mbid>726dafc8-4a20-4834-bc4b-e96c41cbea99</mbid>
<url>https://www.last.fm/music/Ti%C3%ABsto/_/Driving+To+Heaven</url>
<streamable>0</streamable>
<artist><name>Tiësto</name>
<mbid>aabb1d9f-be12-45b3-a84d-a1fc3e8181fd</mbid>
<url>https://www.last.fm/music/Ti%C3%ABsto</url>
</artist>
<image size="small">https://lastfm.freetls.fastly.net/i/u/34s/2a96cbd8b46e442fc41c2b86b821562f.png</image>
<image size="medium">https://lastfm.freetls.fastly.net/i/u/64s/2a96cbd8b46e442fc41c2b86b821562f.png</image>
<image size="large">https://lastfm.freetls.fastly.net/i/u/174s/2a96cbd8b46e442fc41c2b86b821562f.png</image>
<image size="extralarge">https://lastfm.freetls.fastly.net/i/u/300x300/2a96cbd8b46e442fc41c2b86b821562f.png</image>
</track>
<track rank="31"><name>Always Near</name>
<playcount>260330</playcount>
<listeners>73577</listeners>
<url>https://www.last.fm/music/Ti%C3%ABsto/_/Always+Near</url>
<streamable>0</streamable>
<artist><name>Tiësto</name>
<mbid>aabb1d9f-be12-45b3-a84d-a1fc3e8181fd</mbid>
<url>https://www.last.fm/music/Ti%C3%ABsto</url>
</artist>
<image size="small">https://lastfm.freetls.fastly.net/i/u/34s/2a96cbd8b46e442fc41c2b86b821562f.png</image>
<image size="medium">https://lastfm.freetls.fastly.net/i/u/64s/2a96cbd8b46e442fc41c2b86b821562f.png</image>
<image size="large">https://lastfm.freetls.fastly.net/i/u/174s/2a96cbd8b46e442fc41c2b86b821562f.png</image>
<image size="extralarge">https://lastfm.freetls.fastly.net/i/u/300x300/2a96cbd8b46e442fc41c2b86b821562f.png</image>
</track>
<track rank="32"><name>A Tear In The Open</name>
<playcount>244796</playcount>
<listeners>72945</listeners>
<url>https://www.last.fm/music/Ti%C3%ABsto/_/A+Tear+In+The+Open</url>
<streamable>0</streamable>
<artist><name>Tiësto</name>
<mbid>aabb1d9f-be12-45b3-a84d-a1fc3e8181fd</mbid>
<url>https://www.last.fm/music/Ti%C3%ABsto</url>
</artist>
<image size="small">https://lastfm.freetls.fastly.net/i/u/34s/2a96cbd8b46e442fc41c2b86b821562f.png</image>
<image size="medium">https://lastfm.freetls.fastly.net/i/u/64s/2a96cbd8b46e442fc41c2b86b821562f.png</image>
<image size="large">https://lastfm.freetls.fastly.net/i/u/174s/2a96cbd8b46e442fc41c2b86b821562f.png</image>
<image size="extralarge">https://lastfm.freetls.fastly.net/i/u/300x300/2a96cbd8b46e442fc41c2b86b821562f.png</image>
</track>
<track rank="33"><name>Bright Morningstar</name>
<playcount>278866</playcount>
<listeners>71427</listeners>
<mbid>9bfaf46e-1252-46e4-94d5-462ddca05850</mbid>
<url>https://www.last.fm/music/Ti%C3%ABsto/_/Bright+Morningstar</url>
<streamable>0</streamable>
<artist><name>Tiësto</name>
<mbid>aabb1d9f-be12-45b3-a84d-a1fc3e8181fd</mbid>
<url>https://www.last.fm/music/Ti%C3%ABsto</url>
</artist>
<image size="small">https://lastfm.freetls.fastly.net/i/u/34s/2a96cbd8b46e442fc41c2b86b821562f.png</image>
<image size="medium">https://lastfm.freetls.fastly.net/i/u/64s/2a96cbd8b46e442fc41c2b86b821562f.png</image>
<image size="large">https://lastfm.freetls.fastly.net/i/u/174s/2a96cbd8b46e442fc41c2b86b821562f.png</image>
<image size="extralarge">https://lastfm.freetls.fastly.net/i/u/300x300/2a96cbd8b46e442fc41c2b86b821562f.png</image>
</track>
<track rank="34"><name>Sweet Misery</name>
<playcount>255942</playcount>
<listeners>69660</listeners>
<mbid>1ccb7043-4509-4e8f-913a-a14e9c5e530d</mbid>
<url>https://www.last.fm/music/Ti%C3%ABsto/_/Sweet+Misery</url>
<streamable>0</streamable>
<artist><name>Tiësto</name>
<mbid>aabb1d9f-be12-45b3-a84d-a1fc3e8181fd</mbid>
<url>https://www.last.fm/music/Ti%C3%ABsto</url>
</artist>
<image size="small">https://lastfm.freetls.fastly.net/i/u/34s/2a96cbd8b46e442fc41c2b86b821562f.png</image>
<image size="medium">https://lastfm.freetls.fastly.net/i/u/64s/2a96cbd8b46e442fc41c2b86b821562f.png</image>
<image size="large">https://lastfm.freetls.fastly.net/i/u/174s/2a96cbd8b46e442fc41c2b86b821562f.png</image>
<image size="extralarge">https://lastfm.freetls.fastly.net/i/u/300x300/2a96cbd8b46e442fc41c2b86b821562f.png</image>
</track>
<track rank="35"><name>Break My Fall</name>
<playcount>329219</playcount>
<listeners>69394</listeners>
<mbid>4b76817a-9926-45df-92cd-80a67aadd914</mbid>
<url>https://www.last.fm/music/Ti%C3%ABsto/_/Break+My+Fall</url>
<streamable>0</streamable>
<artist><name>Tiësto</name>
<mbid>aabb1d9f-be12-45b3-a84d-a1fc3e8181fd</mbid>
<url>https://www.last.fm/music/Ti%C3%ABsto</url>
</artist>
<image size="small">https://lastfm.freetls.fastly.net/i/u/34s/2a96cbd8b46e442fc41c2b86b821562f.png</image>
<image size="medium">https://lastfm.freetls.fastly.net/i/u/64s/2a96cbd8b46e442fc41c2b86b821562f.png</image>
<image size="large">https://lastfm.freetls.fastly.net/i/u/174s/2a96cbd8b46e442fc41c2b86b821562f.png</image>
<image size="extralarge">https://lastfm.freetls.fastly.net/i/u/300x300/2a96cbd8b46e442fc41c2b86b821562f.png</image>
</track>
<track rank="36"><name>Pump It Louder</name>
<playcount>258245</playcount>
<listeners>67200</listeners>
<url>https://www.last.fm/music/Ti%C3%ABsto/_/Pump+It+Louder</url>
<streamable>0</streamable>
<artist><name>Tiësto</name>
<mbid>aabb1d9f-be12-45b3-a84d-a1fc3e8181fd</mbid>
<url>https://www.last.fm/music/Ti%C3%ABsto</url>
</artist>
<image size="small">https://lastfm.freetls.fastly.net/i/u/34s/2a96cbd8b46e442fc41c2b86b821562f.png</image>
<image size="medium">https://lastfm.freetls.fastly.net/i/u/64s/2a96cbd8b46e442fc41c2b86b821562f.png</image>
<image size="large">https://lastfm.freetls.fastly.net/i/u/174s/2a96cbd8b46e442fc41c2b86b821562f.png</image>
<image size="extralarge">https://lastfm.freetls.fastly.net/i/u/300x300/2a96cbd8b46e442fc41c2b86b821562f.png</image>
</track>
<track rank="37"><name>Flight 643</name>
<playcount>244733</playcount>
<listeners>66633</listeners>
<mbid>82c6f5ba-1a9f-47d5-9710-8fd2ccb4205d</mbid>
<url>https://www.last.fm/music/Ti%C3%ABsto/_/Flight+643</url>
<streamable>0</streamable>
<artist><name>Tiësto</name>
<mbid>aabb1d9f-be12-45b3-a84d-a1fc3e8181fd</mbid>
<url>https://www.last.fm/music/Ti%C3%ABsto</url>
</artist>
<image size="small">https://lastfm.freetls.fastly.net/i/u/34s/2a96cbd8b46e442fc41c2b86b821562f.png</image>
<image size="medium">https://lastfm.freetls.fastly.net/i/u/64s/2a96cbd8b46e442fc41c2b86b821562f.png</image>
<image size="large">https://lastfm.freetls.fastly.net/i/u/174s/2a96cbd8b46e442fc41c2b86b821562f.png</image>
<image size="extralarge">https://lastfm.freetls.fastly.net/i/u/300x300/2a96cbd8b46e442fc41c2b86b821562f.png</image>
</track>
<track rank="38"><name>All Nighter</name>
<playcount>294877</playcount>
<listeners>63271</listeners>
<url>https://www.last.fm/music/Ti%C3%ABsto/_/All+Nighter</url>
<streamable>0</streamable>
<artist><name>Tiësto</name>
<mbid>aabb1d9f-be12-45b3-a84d-a1fc3e8181fd</mbid>
<url>https://www.last.fm/music/Ti%C3%ABsto</url>
</artist>
<image size="small">https://lastfm.freetls.fastly.net/i/u/34s/2a96cbd8b46e442fc41c2b86b821562f.png</image>
<image size="medium">https://lastfm.freetls.fastly.net/i/u/64s/2a96cbd8b46e442fc41c2b86b821562f.png</image>
<image size="large">https://lastfm.freetls.fastly.net/i/u/174s/2a96cbd8b46e442fc41c2b86b821562f.png</image>
<image size="extralarge">https://lastfm.freetls.fastly.net/i/u/300x300/2a96cbd8b46e442fc41c2b86b821562f.png</image>
</track>
<track rank="39"><name>Drifting</name>
<playcount>253945</playcount>
<listeners>62068</listeners>
<url>https://www.last.fm/music/Ti%C3%ABsto/_/Drifting</url>
<streamable>0</streamable>
<artist><name>Tiësto</name>
<mbid>aabb1d9f-be12-45b3-a84d-a1fc3e8181fd</mbid>
<url>https://www.last.fm/music/Ti%C3%ABsto</url>
</artist>
<image size="small">https://lastfm.freetls.fastly.net/i/u/34s/2a96cbd8b46e442fc41c2b86b821562f.png</image>
<image size="medium">https://lastfm.freetls.fastly.net/i/u/64s/2a96cbd8b46e442fc41c2b86b821562f.png</image>
<image size="large">https://lastfm.freetls.fastly.net/i/u/174s/2a96cbd8b46e442fc41c2b86b821562f.png</image>
<image size="extralarge">https://lastfm.freetls.fastly.net/i/u/300x300/2a96cbd8b46e442fc41c2b86b821562f.png</image>
</track>
<track rank="40"><name>UR</name>
<playcount>226194</playcount>
<listeners>61806</listeners>
<mbid>d3f79e3b-a774-48b2-bf26-c4f9e8ab8f3f</mbid>
<url>https://www.last.fm/music/Ti%C3%ABsto/_/UR</url>
<streamable>0</streamable>
<artist><name>Tiësto</name>
<mbid>aabb1d9f-be12-45b3-a84d-a1fc3e8181fd</mbid>
<url>https://www.last.fm/music/Ti%C3%ABsto</url>
</artist>
<image size="small">https://lastfm.freetls.fastly.net/i/u/34s/2a96cbd8b46e442fc41c2b86b821562f.png</image>
<image size="medium">https://lastfm.freetls.fastly.net/i/u/64s/2a96cbd8b46e442fc41c2b86b821562f.png</image>
<image size="large">https://lastfm.freetls.fastly.net/i/u/174s/2a96cbd8b46e442fc41c2b86b821562f.png</image>
<image size="extralarge">https://lastfm.freetls.fastly.net/i/u/300x300/2a96cbd8b46e442fc41c2b86b821562f.png</image>
</track>
<track rank="41"><name>On My Way</name>
<playcount>285515</playcount>
<listeners>60819</listeners>
<url>https://www.last.fm/music/Ti%C3%ABsto/_/On+My+Way</url>
<streamable>0</streamable>
<artist><name>Tiësto</name>
<mbid>aabb1d9f-be12-45b3-a84d-a1fc3e8181fd</mbid>
<url>https://www.last.fm/music/Ti%C3%ABsto</url>
</artist>
<image size="small">https://lastfm.freetls.fastly.net/i/u/34s/2a96cbd8b46e442fc41c2b86b821562f.png</image>
<image size="medium">https://lastfm.freetls.fastly.net/i/u/64s/2a96cbd8b46e442fc41c2b86b821562f.png</image>
<image size="large">https://lastfm.freetls.fastly.net/i/u/174s/2a96cbd8b46e442fc41c2b86b821562f.png</image>
<image size="extralarge">https://lastfm.freetls.fastly.net/i/u/300x300/2a96cbd8b46e442fc41c2b86b821562f.png</image>
</track>
<track rank="42"><name>Louder Than Boom</name>
<playcount>236238</playcount>
<listeners>60675</listeners>
<mbid>f4640617-1776-41c1-bd5f-e45c8a2fc525</mbid>
<url>https://www.last.fm/music/Ti%C3%ABsto/_/Louder+Than+Boom</url>
<streamable>0</streamable>
<artist><name>Tiësto</name>
<mbid>aabb1d9f-be12-45b3-a84d-a1fc3e8181fd</mbid>
<url>https://www.last.fm/music/Ti%C3%ABsto</url>
</artist>
<image size="small">https://lastfm.freetls.fastly.net/i/u/34s/2a96cbd8b46e442fc41c2b86b821562f.png</image>
<image size="medium">https://lastfm.freetls.fastly.net/i/u/64s/2a96cbd8b46e442fc41c2b86b821562f.png</image>
<image size="large">https://lastfm.freetls.fastly.net/i/u/174s/2a96cbd8b46e442fc41c2b86b821562f.png</image>
<image size="extralarge">https://lastfm.freetls.fastly.net/i/u/300x300/2a96cbd8b46e442fc41c2b86b821562f.png</image>
</track>
<track rank="43"><name>In My Memory</name>
<playcount>306856</playcount>
<listeners>59846</listeners>
<mbid>f2af208c-8d12-4363-ab88-a85ccbd322b0</mbid>
<url>https://www.last.fm/music/Ti%C3%ABsto/_/In+My+Memory</url>
<streamable>0</streamable>
<artist><name>Tiësto</name>
<mbid>aabb1d9f-be12-45b3-a84d-a1fc3e8181fd</mbid>
<url>https://www.last.fm/music/Ti%C3%ABsto</url>
</artist>
<image size="small">https://lastfm.freetls.fastly.net/i/u/34s/2a96cbd8b46e442fc41c2b86b821562f.png</image>
<image size="medium">https://lastfm.freetls.fastly.net/i/u/64s/2a96cbd8b46e442fc41c2b86b821562f.png</image>
<image size="large">https://lastfm.freetls.fastly.net/i/u/174s/2a96cbd8b46e442fc41c2b86b821562f.png</image>
<image size="extralarge">https://lastfm.freetls.fastly.net/i/u/300x300/2a96cbd8b46e442fc41c2b86b821562f.png</image>
</track>
<track rank="44"><name>Everything</name>
<playcount>263147</playcount>
<listeners>58359</listeners>
<url>https://www.last.fm/music/Ti%C3%ABsto/_/Everything</url>
<streamable>0</streamable>
<artist><name>Tiësto</name>
<mbid>aabb1d9f-be12-45b3-a84d-a1fc3e8181fd</mbid>
<url>https://www.last.fm/music/Ti%C3%ABsto</url>
</artist>
<image size="small">https://lastfm.freetls.fastly.net/i/u/34s/2a96cbd8b46e442fc41c2b86b821562f.png</image>
<image size="medium">https://lastfm.freetls.fastly.net/i/u/64s/2a96cbd8b46e442fc41c2b86b821562f.png</image>
<image size="large">https://lastfm.freetls.fastly.net/i/u/174s/2a96cbd8b46e442fc41c2b86b821562f.png</image>
<image size="extralarge">https://lastfm.freetls.fastly.net/i/u/300x300/2a96cbd8b46e442fc41c2b86b821562f.png</image>
</track>
<track rank="45"><name>Split (Only U)</name>
<playcount>273621</playcount>
<listeners>58133</listeners>
<url>https://www.last.fm/music/Ti%C3%ABsto/_/Split+(Only+U)</url>
<streamable>0</streamable>
<artist><name>Tiësto</name>
<mbid>aabb1d9f-be12-45b3-a84d-a1fc3e8181fd</mbid>
<url>https://www.last.fm/music/Ti%C3%ABsto</url>
</artist>
<image size="small">https://lastfm.freetls.fastly.net/i/u/34s/2a96cbd8b46e442fc41c2b86b821562f.png</image>
<image size="medium">https://lastfm.freetls.fastly.net/i/u/64s/2a96cbd8b46e442fc41c2b86b821562f.png</image>
<image size="large">https://lastfm.freetls.fastly.net/i/u/174s/2a96cbd8b46e442fc41c2b86b821562f.png</image>
<image size="extralarge">https://lastfm.freetls.fastly.net/i/u/300x300/2a96cbd8b46e442fc41c2b86b821562f.png</image>
</track>
<track rank="46"><name>LA Ride</name>
<playcount>207946</playcount>
<listeners>56713</listeners>
<url>https://www.last.fm/music/Ti%C3%ABsto/_/LA+Ride</url>
<streamable>0</streamable>
<artist><name>Tiësto</name>
<mbid>aabb1d9f-be12-45b3-a84d-a1fc3e8181fd</mbid>
<url>https://www.last.fm/music/Ti%C3%ABsto</url>
</artist>
<image size="small">https://lastfm.freetls.fastly.net/i/u/34s/2a96cbd8b46e442fc41c2b86b821562f.png</image>
<image size="medium">https://lastfm.freetls.fastly.net/i/u/64s/2a96cbd8b46e442fc41c2b86b821562f.png</image>
<image size="large">https://lastfm.freetls.fastly.net/i/u/174s/2a96cbd8b46e442fc41c2b86b821562f.png</image>
<image size="extralarge">https://lastfm.freetls.fastly.net/i/u/300x300/2a96cbd8b46e442fc41c2b86b821562f.png</image>
</track>
<track rank="47"><name>Bend It Like You Don&apos;t Care</name>
<playcount>203178</playcount>
<listeners>54701</listeners>
<url>https://www.last.fm/music/Ti%C3%ABsto/_/Bend+It+Like+You+Don%27t+Care</url>
<streamable>0</streamable>
<artist><name>Tiësto</name>
<mbid>aabb1d9f-be12-45b3-a84d-a1fc3e8181fd</mbid>
<url>https://www.last.fm/music/Ti%C3%ABsto</url>
</artist>
<image size="small">https://lastfm.freetls.fastly.net/i/u/34s/2a96cbd8b46e442fc41c2b86b821562f.png</image>
<image size="medium">https://lastfm.freetls.fastly.net/i/u/64s/2a96cbd8b46e442fc41c2b86b821562f.png</image>
<image size="large">https://lastfm.freetls.fastly.net/i/u/174s/2a96cbd8b46e442fc41c2b86b821562f.png</image>
<image size="extralarge">https://lastfm.freetls.fastly.net/i/u/300x300/2a96cbd8b46e442fc41c2b86b821562f.png</image>
</track>
<track rank="48"><name>Suburban Train</name>
<playcount>224359</playcount>
<listeners>54493</listeners>
<mbid>c3ea4054-3430-4062-8860-35d7cc529f4c</mbid>
<url>https://www.last.fm/music/Ti%C3%ABsto/_/Suburban+Train</url>
<streamable>0</streamable>
<artist><name>Tiësto</name>
<mbid>aabb1d9f-be12-45b3-a84d-a1fc3e8181fd</mbid>
<url>https://www.last.fm/music/Ti%C3%ABsto</url>
</artist>
<image size="small">https://lastfm.freetls.fastly.net/i/u/34s/2a96cbd8b46e442fc41c2b86b821562f.png</image>
<image size="medium">https://lastfm.freetls.fastly.net/i/u/64s/2a96cbd8b46e442fc41c2b86b821562f.png</image>
<image size="large">https://lastfm.freetls.fastly.net/i/u/174s/2a96cbd8b46e442fc41c2b86b821562f.png</image>
<image size="extralarge">https://lastfm.freetls.fastly.net/i/u/300x300/2a96cbd8b46e442fc41c2b86b821562f.png</image>
</track>
<track rank="49"><name>Let’s Go</name>
<playcount>155950</playcount>
<listeners>52153</listeners>
<url>https://www.last.fm/music/Ti%C3%ABsto/_/Let%E2%80%99s+Go</url>
<streamable>0</streamable>
<artist><name>Tiësto</name>
<mbid>aabb1d9f-be12-45b3-a84d-a1fc3e8181fd</mbid>
<url>https://www.last.fm/music/Ti%C3%ABsto</url>
</artist>
<image size="small">https://lastfm.freetls.fastly.net/i/u/34s/2a96cbd8b46e442fc41c2b86b821562f.png</image>
<image size="medium">https://lastfm.freetls.fastly.net/i/u/64s/2a96cbd8b46e442fc41c2b86b821562f.png</image>
<image size="large">https://lastfm.freetls.fastly.net/i/u/174s/2a96cbd8b46e442fc41c2b86b821562f.png</image>
<image size="extralarge">https://lastfm.freetls.fastly.net/i/u/300x300/2a96cbd8b46e442fc41c2b86b821562f.png</image>
</track>
<track rank="50"><name>Surrounded by Light</name>
<playcount>178881</playcount>
<listeners>50850</listeners>
<mbid>d9bda667-4208-4304-a835-175ccd473469</mbid>
<url>https://www.last.fm/music/Ti%C3%ABsto/_/Surrounded+by+Light</url>
<streamable>0</streamable>
<artist><name>Tiësto</name>
<mbid>aabb1d9f-be12-45b3-a84d-a1fc3e8181fd</mbid>
<url>https://www.last.fm/music/Ti%C3%ABsto</url>
</artist>
<image size="small">https://lastfm.freetls.fastly.net/i/u/34s/2a96cbd8b46e442fc41c2b86b821562f.png</image>
<image size="medium">https://lastfm.freetls.fastly.net/i/u/64s/2a96cbd8b46e442fc41c2b86b821562f.png</image>
<image size="large">https://lastfm.freetls.fastly.net/i/u/174s/2a96cbd8b46e442fc41c2b86b821562f.png</image>
<image size="extralarge">https://lastfm.freetls.fastly.net/i/u/300x300/2a96cbd8b46e442fc41c2b86b821562f.png</image>
</track>
</toptracks>
</lfm>
